{
  "updated": "2026-05-15T11:59:24.410Z",
  "featured": {
    "category": "betrayal",
    "kicker": "Both parties fail again",
    "headline": "House barely rejects limits on Iran war as GOP defections grow",
    "dek": "Bipartisan resistance emerges to congressional war powers oversight as both parties enable executive overreach on military action.",
    "votes_r": 28,
    "votes_d": 31,
    "votes_yes": 59,
    "votes_no": 201,
    "source": "Politico"
  },
  "articles": [
    {
      "id": 1,
      "category": "betrayal",
      "headline": "This California Congressional Hopeful Opposes a Billionaire Tax. So Do His Tech CEO Backers.",
      "meta": "Politics · today",
      "url": "https://theintercept.com"
    },
    {
      "id": 2,
      "category": "betrayal",
      "headline": "A Unique Oregon Law Allows It to Block Healthcare Deals. In Five Years, the State Hasn't Done So Once.",
      "meta": "Politics · today",
      "url": "https://feeds.propublica.org"
    },
    {
      "id": 3,
      "category": "betrayal",
      "headline": "Nervous Republicans weigh their options amid White House's ballroom lobbying blitz",
      "meta": "Politics · today",
      "url": "https://rss.politico.com"
    },
    {
      "id": 4,
      "category": "betrayal",
      "headline": "House Ethics panel investigating Chuck Edwards for sexual misconduct",
      "meta": "Politics · today",
      "url": "https://rss.politico.com"
    },
    {
      "id": 5,
      "category": "betrayal",
      "headline": "Key Jeffries ally endorses aggressive tactics to create more blue seats",
      "meta": "Politics · today",
      "url": "https://rss.politico.com"
    }
  ],
  "stats": {
    "shared_donor_dollars": "$4.2B",
    "bipartisan_yes_votes": "847",
    "wars_since_2000": "7"
  },
  "hall_of_shame": [
    {
      "initials": "MM",
      "party": "r",
      "name": "M. McConnell",
      "sin": "$45M pharma, voted against price caps"
    },
    {
      "initials": "NP",
      "party": "d",
      "name": "N. Pelosi",
      "sin": "Tech stock trades during antitrust hearings"
    },
    {
      "initials": "LC",
      "party": "r",
      "name": "L. Cheney",
      "sin": "Halliburton ties, Iraq war, no-bid contracts"
    },
    {
      "initials": "CS",
      "party": "d",
      "name": "C. Schumer",
      "sin": "Wall St. top recipient, blocked Glass-Steagall reversal"
    }
  ]
}