{
  "updated": "2026-05-16T19:14:31.637Z",
  "featured": {
    "category": "betrayal",
    "kicker": "Both parties fail again",
    "headline": "A Unique Oregon Law Allows It to Block Healthcare Deals. In Five Years, the State Hasn't Done So Once.",
    "dek": "Despite having unprecedented power to stop harmful healthcare mergers, Oregon officials have rubber-stamped every deal while patients suffer.",
    "votes_r": 0,
    "votes_d": 0,
    "votes_yes": 0,
    "votes_no": 0,
    "source": "ProPublica"
  },
  "articles": [
    {
      "id": 1,
      "category": "betrayal",
      "headline": "Why Have Immigration Agents Detained This American Citizen Three Times?",
      "meta": "Politics · today",
      "url": "https://feeds.propublica.org"
    },
    {
      "id": 2,
      "category": "betrayal",
      "headline": "Counterterrorism Czar's Blueprint Targets Leftists, Ignores Far-Right Violence and Heaps Praise on Trump",
      "meta": "Politics · today",
      "url": "https://feeds.propublica.org"
    },
    {
      "id": 3,
      "category": "betrayal",
      "headline": "CDC Didn't Tell New York About Resident on Hantavirus-Plagued Cruise",
      "meta": "Politics · today",
      "url": "https://theintercept.com"
    },
    {
      "id": 4,
      "category": "betrayal",
      "headline": "In a Private Meeting, Colorado Marijuana Regulators Acknowledge the Extent of Illegal Hemp Sales",
      "meta": "Politics · today",
      "url": "https://feeds.propublica.org"
    },
    {
      "id": 5,
      "category": "betrayal",
      "headline": "Trump pushes to attach his SAVE act to must-pass bipartisan bills",
      "meta": "Politics · today",
      "url": "https://rss.politico.com"
    }
  ],
  "stats": {
    "shared_donor_dollars": "$4.2B",
    "bipartisan_yes_votes": "847",
    "wars_since_2000": "7"
  },
  "hall_of_shame": [
    {
      "initials": "MM",
      "party": "r",
      "name": "M. McConnell",
      "sin": "$45M pharma, voted against price caps"
    },
    {
      "initials": "NP",
      "party": "d",
      "name": "N. Pelosi",
      "sin": "Tech stock trades during antitrust hearings"
    },
    {
      "initials": "LC",
      "party": "r",
      "name": "L. Cheney",
      "sin": "Halliburton ties, Iraq war, no-bid contracts"
    },
    {
      "initials": "CS",
      "party": "d",
      "name": "C. Schumer",
      "sin": "Wall St. top recipient, blocked Glass-Steagall reversal"
    }
  ]
}